{
	"miniprogramRoot": "dist/",
	"projectname": "cross-app-demo",
	"description": "直播多端demo",
	"appid": "wx0e7ee98e584ab41d",
	"setting": {
		"urlCheck": true,
		"scopeDataCheck": false,
		"coverView": true,
		"es6": false,
		"postcss": false,
		"compileHotReLoad": false,
		"preloadBackgroundData": false,
		"minified": false,
		"autoAudits": false,
		"newFeature": false,
		"uglifyFileName": false,
		"uploadWithSourceMap": true,
		"useIsolateContext": true,
		"nodeModules": false,
		"enhance": false,
		"useCompilerModule": true,
		"userConfirmedUseCompilerModuleSwitch": false,
		"showShadowRootInWxmlPanel": true
	},
	"compileType": "miniprogram",
	"simulatorType": "wechat",
	"simulatorPluginLibVersion": {},
	"condition": {
		"search": {
			"current": -1,
			"list": []
		},
		"conversation": {
			"current": -1,
			"list": []
		},
		"plugin": {
			"current": -1,
			"list": []
		},
		"game": {
			"current": -1,
			"list": []
		},
		"gamePlugin": {
			"current": -1,
			"list": []
		},
		"miniprogram": {
			"current": -1,
			"list": [
				{
					"id": -1,
					"name": "pages/onepage/index",
					"pathName": "pages/onepage/index",
					"scene": null
				}
			]
		}
	}
}